py_reconciliation_service_api/__init__.py
py_reconciliation_service_api/models/__init__.py
py_reconciliation_service_api/models/manifest.py
py_reconciliation_service_api/models/reconciliation.py
py_reconciliation_service_api/py.typed
py_reconciliation_service_api-0.2.1.dist-info/METADATA
py_reconciliation_service_api-0.2.1.dist-info/WHEEL
py_reconciliation_service_api-0.2.1.dist-info/RECORD
